assemblyai/__init__.py
assemblyai/__version__.py
assemblyai/api.py
assemblyai/client.py
assemblyai/extras.py
assemblyai/lemur.py
assemblyai/transcriber.py
assemblyai/types.py
assemblyai/streaming/__init__.py
assemblyai/streaming/v3/__init__.py
assemblyai/streaming/v3/client.py
assemblyai/streaming/v3/models.py
assemblyai-0.48.4.dist-info/LICENSE
assemblyai-0.48.4.dist-info/METADATA
assemblyai-0.48.4.dist-info/WHEEL
assemblyai-0.48.4.dist-info/top_level.txt
assemblyai-0.48.4.dist-info/RECORD
