Metadata-Version: 2.1
Name: assemblyai
Version: 0.48.4
Summary: AssemblyAI Python SDK
Home-page: https://github.com/AssemblyAI/assemblyai-python-sdk
Author: AssemblyAI
Author-email: engineering.sdk@assemblyai.com
License: MIT License
Project-URL: Code, https://github.com/AssemblyAI/assemblyai-python-sdk
Project-URL: Issues, https://github.com/AssemblyAI/assemblyai-python-sdk/issues
Project-URL: Documentation, https://github.com/AssemblyAI/assemblyai-python-sdk/blob/master/README.md
Project-URL: API Documentation, https://www.assemblyai.com/docs/
Project-URL: Website, https://assemblyai.com/
Classifier: Development Status :: 3 - Alpha
Classifier: Intended Audience :: Developers
Classifier: Intended Audience :: Science/Research
Classifier: License :: OSI Approved :: MIT License
Classifier: Natural Language :: English
Classifier: Topic :: Scientific/Engineering :: Artificial Intelligence
Classifier: Topic :: Software Development :: Libraries
Classifier: Topic :: Software Development :: Libraries :: Python Modules
Classifier: Programming Language :: Python :: 3
Classifier: Programming Language :: Python :: 3.8
Classifier: Programming Language :: Python :: 3.9
Classifier: Programming Language :: Python :: 3.10
Classifier: Programming Language :: Python :: 3.11
Classifier: Programming Language :: Python :: 3.12
Classifier: Programming Language :: Python :: 3.13
Classifier: Programming Language :: Python :: 3.14
Requires-Python: >=3.8
License-File: LICENSE
Requires-Dist: httpx >=0.19.0
Requires-Dist: typing-extensions >=3.7
Requires-Dist: websockets >=11.0
Requires-Dist: pydantic >=1.10.17 ; python_version < "3.14"
Requires-Dist: pydantic >=2.0 ; python_version >= "3.14"
Requires-Dist: pydantic-settings >=2.0 ; python_version >= "3.14"
Provides-Extra: extras
Requires-Dist: pyaudio >=0.2.13 ; extra == 'extras'
